[
  {
    "zoneId": "Z1N",
    "risk": 0.101,
    "drivers": [
      {
        "feature": "hermann_level",
        "contribution": 0.14
      },
      {
        "feature": "grafton_level",
        "contribution": 0.32
      },
      {
        "feature": "daily_precip",
        "contribution": 0.54
      }
    ],
    "thresholdBand": "Low",
    "etaHours": 18
  },
  {
    "zoneId": "Z1S",
    "risk": 0.1,
    "drivers": [
      {
        "feature": "hermann_level",
        "contribution": 0.14
      },
      {
        "feature": "grafton_level",
        "contribution": 0.32
      },
      {
        "feature": "daily_precip",
        "contribution": 0.54
      }
    ],
    "thresholdBand": "Low",
    "etaHours": 18
  },
  {
    "zoneId": "Z2",
    "risk": 0.089,
    "drivers": [
      {
        "feature": "hermann_level",
        "contribution": 0.14
      },
      {
        "feature": "grafton_level",
        "contribution": 0.32
      },
      {
        "feature": "daily_precip",
        "contribution": 0.54
      }
    ],
    "thresholdBand": "Low",
    "etaHours": 18
  },
  {
    "zoneId": "Z3",
    "risk": 0.071,
    "drivers": [
      {
        "feature": "hermann_level",
        "contribution": 0.14
      },
      {
        "feature": "grafton_level",
        "contribution": 0.32
      },
      {
        "feature": "daily_precip",
        "contribution": 0.54
      }
    ],
    "thresholdBand": "Low",
    "etaHours": 18
  },
  {
    "zoneId": "Z4",
    "risk": 0.074,
    "drivers": [
      {
        "feature": "hermann_level",
        "contribution": 0.14
      },
      {
        "feature": "grafton_level",
        "contribution": 0.32
      },
      {
        "feature": "daily_precip",
        "contribution": 0.54
      }
    ],
    "thresholdBand": "Low",
    "etaHours": 18
  },
  {
    "zoneId": "ZC",
    "risk": 0.087,
    "drivers": [
      {
        "feature": "hermann_level",
        "contribution": 0.14
      },
      {
        "feature": "grafton_level",
        "contribution": 0.32
      },
      {
        "feature": "daily_precip",
        "contribution": 0.54
      }
    ],
    "thresholdBand": "Low",
    "etaHours": 18
  }
]