[
  {
    "zoneId": "Z1N",
    "risk": 0.55,
    "drivers": [
      {
        "feature": "hermann_level",
        "contribution": 0.48
      },
      {
        "feature": "grafton_level",
        "contribution": 0.52
      },
      {
        "feature": "daily_precip",
        "contribution": 0.0
      }
    ],
    "thresholdBand": "High",
    "etaHours": 12
  },
  {
    "zoneId": "Z1S",
    "risk": 0.541,
    "drivers": [
      {
        "feature": "hermann_level",
        "contribution": 0.48
      },
      {
        "feature": "grafton_level",
        "contribution": 0.52
      },
      {
        "feature": "daily_precip",
        "contribution": 0.0
      }
    ],
    "thresholdBand": "High",
    "etaHours": 12
  },
  {
    "zoneId": "Z2",
    "risk": 0.485,
    "drivers": [
      {
        "feature": "hermann_level",
        "contribution": 0.48
      },
      {
        "feature": "grafton_level",
        "contribution": 0.52
      },
      {
        "feature": "daily_precip",
        "contribution": 0.0
      }
    ],
    "thresholdBand": "Moderate",
    "etaHours": 12
  },
  {
    "zoneId": "Z3",
    "risk": 0.387,
    "drivers": [
      {
        "feature": "hermann_level",
        "contribution": 0.48
      },
      {
        "feature": "grafton_level",
        "contribution": 0.52
      },
      {
        "feature": "daily_precip",
        "contribution": 0.0
      }
    ],
    "thresholdBand": "Moderate",
    "etaHours": 12
  },
  {
    "zoneId": "Z4",
    "risk": 0.401,
    "drivers": [
      {
        "feature": "hermann_level",
        "contribution": 0.48
      },
      {
        "feature": "grafton_level",
        "contribution": 0.52
      },
      {
        "feature": "daily_precip",
        "contribution": 0.0
      }
    ],
    "thresholdBand": "Moderate",
    "etaHours": 12
  },
  {
    "zoneId": "ZC",
    "risk": 0.471,
    "drivers": [
      {
        "feature": "hermann_level",
        "contribution": 0.48
      },
      {
        "feature": "grafton_level",
        "contribution": 0.52
      },
      {
        "feature": "daily_precip",
        "contribution": 0.0
      }
    ],
    "thresholdBand": "Moderate",
    "etaHours": 12
  }
]